[
    {
        "start_date": "15-11-2023",
        "end_date": "15-12-2023",
        "environment": "Test / Perftest",
        "business_area": "cross-cutting",
        "change_jira_id": "DTSPO-15384",
        "issue_link": "https://github.com/hmcts/auto-shutdown/issues/219"
    },
    {
        "start_date": "04-12-2023",
        "end_date": "04-12-2023",
        "request_type": "stop",
        "environment": "PTL",
        "business_area": "cft",
        "change_jira_id": "https://tools.hmcts.net/jira/browse/RBC-17267",
        "issue_link": "https://github.com/hmcts/auto-shutdown/issues/248"
    },
    {
        "start_date": "04-12-2023",
        "end_date": "04-12-2023",
        "request_type": "stop",
        "environment": [
            "AAT / Staging",
            "Preview / Dev"
        ],
        "business_area": "cft",
        "change_jira_id": "https://tools.hmcts.net/jira/browse/RBC-17267",
        "issue_link": "https://github.com/hmcts/auto-shutdown/issues/249"
    },
    {
        "start_date": "04-12-2023",
        "end_date": "04-12-2023",
        "request_type": "stop",
        "environment": "Demo",
        "business_area": "cft",
        "change_jira_id": "DTSPB-3601",
        "issue_link": "https://github.com/hmcts/auto-shutdown/issues/251"
    },
    {
        "start_date": "04-12-2023",
        "end_date": "05-12-2023",
        "request_type": "stop",
        "environment": [
            "AAT / Staging",
            "Preview / Dev",
            "Demo",
            "PTL"
        ],
        "business_area": "cft",
        "change_jira_id": "CIV-11813",
        "issue_link": "https://github.com/hmcts/auto-shutdown/issues/252"
    },
    {
        "start_date": "06-12-2023",
        "end_date": "07-12-2023",
        "request_type": "stop",
        "environment": [
            "AAT / Staging",
            "Preview / Dev",
            "PTL"
        ],
        "business_area": "cft",
        "change_jira_id": "https://mojcppprod.service-now.com/nav_to.do?uri=%2Fchange_request.do%3Fsys_id%3Dce22a2d51b92f5504e6f2fc7bd4bcb8c",
        "issue_link": "https://github.com/hmcts/auto-shutdown/issues/253"
    },
    {
        "start_date": "11-12-2023",
        "end_date": "11-12-2023",
        "request_type": "stop",
        "environment": [
            "AAT / Staging",
            "Preview / Dev",
            "PTL"
        ],
        "business_area": "cft",
        "change_jira_id": "CHG5014385",
        "issue_link": "https://github.com/hmcts/auto-shutdown/issues/254"
    }
]