[
    {
        "start_date": "12-09-2024",
        "end_date": "12-09-2024",
        "request_type": "stop",
        "environment": [
            "AAT / Staging",
            "Preview / Dev",
            "PTL"
        ],
        "business_area": "cft",
        "change_jira_id": "https://tools.hmcts.net/jira/browse/RR-3088",
        "stay_on_late": "Yes",
        "issue_link": "https://github.com/hmcts/auto-shutdown/issues/377"
    },
    {
        "start_date": "07-06-2024",
        "end_date": "08-06-2024",
        "request_type": "stop",
        "environment": [
            "AAT / Staging",
            " PTL"
        ],
        "business_area": "cross-cutting",
        "change_jira_id": "JM-7477 in CGI Jira",
        "stay_on_late": "Yes",
        "justification": "Approaching go-live, testing activities needed over the weekend",
        "issue_link": "https://github.com/hmcts/auto-shutdown/issues/542"
    },
    {
        "start_date": "11-06-2024",
        "end_date": "11-06-2024",
        "request_type": "stop",
        "environment": [
            "AAT / Staging",
            " Preview / Dev",
            " PTL"
        ],
        "business_area": "cft",
        "change_jira_id": "CHG5016571",
        "stay_on_late": "No",
        "justification": "OOH release",
        "issue_link": "https://github.com/hmcts/auto-shutdown/issues/545"
    },
    {
        "start_date": "11-06-2024",
        "end_date": "11-06-2024",
        "request_type": "stop",
        "environment": [
            "AAT / Staging",
            " Preview / Dev",
            " Demo",
            " PTL"
        ],
        "business_area": "cft",
        "change_jira_id": "CHG5016526",
        "stay_on_late": "No",
        "justification": "SDO-R2 Release",
        "issue_link": "https://github.com/hmcts/auto-shutdown/issues/548"
    }
]